llama_index/llms/optimum_intel/__init__.py
llama_index/llms/optimum_intel/base.py
llama_index_llms_optimum_intel-0.4.1.dist-info/METADATA
llama_index_llms_optimum_intel-0.4.1.dist-info/WHEEL
llama_index_llms_optimum_intel-0.4.1.dist-info/licenses/LICENSE
llama_index_llms_optimum_intel-0.4.1.dist-info/RECORD
